{
	"info": {
		"_postman_id": "a5674562-9b9e-422c-8e90-2d105e9007c4",
		"name": "User",
		"schema": "https://schema.getpostman.com/json/collection/v2.1.0/collection.json",
		"_exporter_id": "32851632"
	},
	"item": [
		{
			"name": "Create User",
			"request": {
				"method": "POST",
				"header": [],
				"body": {
					"mode": "raw",
					"raw": "{\n    \"id\":\"3\",\n    \"username\":\"Kyle\",\n    \"email\":\"kyle2003@gmail.com\",\n    \"password\":\"kyle\"\n}",
					"options": {
						"raw": {
							"language": "json"
						}
					}
				},
				"url": {
					"raw": "http://localhost:8888/mayakitchen/API/Createuser.php?",
					"protocol": "http",
					"host": [
						"localhost"
					],
					"port": "8888",
					"path": [
						"mayakitchen",
						"API",
						"Createuser.php"
					],
					"query": [
						{
							"key": "",
							"value": null
						}
					]
				}
			},
			"response": []
		},
		{
			"name": "Getusers",
			"protocolProfileBehavior": {
				"disableBodyPruning": true
			},
			"request": {
				"method": "GET",
				"header": [],
				"body": {
					"mode": "raw",
					"raw": "{\n    \"id\":1,\n    \"username\":\"kylie\",\n    \"email\":\"kylie2003@gmail.com\",\n    \"password\":12345\n}",
					"options": {
						"raw": {
							"language": "json"
						}
					}
				},
				"url": {
					"raw": "http://localhost:8888/mayakitchen/API/getUsers.php?",
					"protocol": "http",
					"host": [
						"localhost"
					],
					"port": "8888",
					"path": [
						"mayakitchen",
						"API",
						"getUsers.php"
					],
					"query": [
						{
							"key": "",
							"value": null
						}
					]
				}
			},
			"response": []
		},
		{
			"name": "GetUser",
			"protocolProfileBehavior": {
				"disableBodyPruning": true
			},
			"request": {
				"method": "GET",
				"header": [],
				"body": {
					"mode": "raw",
					"raw": "{\n    \"id\":1,\n    \"username\":\"kylie\",\n    \"email\":\"kylie2003@gmail.com\",\n    \"password\":12345\n}",
					"options": {
						"raw": {
							"language": "json"
						}
					}
				},
				"url": {
					"raw": "http://localhost:8888/mayakitchen/API/getUser.php?",
					"protocol": "http",
					"host": [
						"localhost"
					],
					"port": "8888",
					"path": [
						"mayakitchen",
						"API",
						"getUser.php"
					],
					"query": [
						{
							"key": "",
							"value": null
						}
					]
				}
			},
			"response": []
		},
		{
			"name": "delete",
			"request": {
				"method": "DELETE",
				"header": [],
				"body": {
					"mode": "raw",
					"raw": "",
					"options": {
						"raw": {
							"language": "json"
						}
					}
				},
				"url": {
					"raw": "http://localhost:8888/mayakitchen/API/deleteUser.php?id=3",
					"protocol": "http",
					"host": [
						"localhost"
					],
					"port": "8888",
					"path": [
						"mayakitchen",
						"API",
						"deleteUser.php"
					],
					"query": [
						{
							"key": "id",
							"value": "3"
						}
					]
				}
			},
			"response": []
		},
		{
			"name": "Updateuser",
			"request": {
				"method": "PUT",
				"header": [],
				"body": {
					"mode": "raw",
					"raw": "{\n    \"id\":\"1\",\n    \"username\":\"kylie\",\n    \"email\":\"kylie2003@gmail.com\",\n    \"password\":\"kylie\"\n}",
					"options": {
						"raw": {
							"language": "json"
						}
					}
				},
				"url": {
					"raw": "http://localhost:8888/mayakitchen/API/updateuser.php?id=1",
					"protocol": "http",
					"host": [
						"localhost"
					],
					"port": "8888",
					"path": [
						"mayakitchen",
						"API",
						"updateuser.php"
					],
					"query": [
						{
							"key": "id",
							"value": "1"
						}
					]
				}
			},
			"response": []
		},
		{
			"name": "changeuserpassword",
			"request": {
				"method": "PATCH",
				"header": [],
				"body": {
					"mode": "raw",
					"raw": "{\n    \"id\":\"1\",\n    \"new_password\":\"12345\"\n}",
					"options": {
						"raw": {
							"language": "json"
						}
					}
				},
				"url": {
					"raw": "http://localhost:8888/mayakitchen/API/changeUserPassword.php?id=1",
					"protocol": "http",
					"host": [
						"localhost"
					],
					"port": "8888",
					"path": [
						"mayakitchen",
						"API",
						"changeUserPassword.php"
					],
					"query": [
						{
							"key": "id",
							"value": "1"
						}
					]
				}
			},
			"response": []
		},
		{
			"name": "getspecialofferdetail",
			"protocolProfileBehavior": {
				"disableBodyPruning": true
			},
			"request": {
				"method": "GET",
				"header": [],
				"body": {
					"mode": "raw",
					"raw": "{\n    \"queryString\": \"SELECT * FROM special_offers\"\n}\n",
					"options": {
						"raw": {
							"language": "json"
						}
					}
				},
				"url": {
					"raw": "http://localhost:8888/mayakitchen/API/getSpecialOffers.php?",
					"protocol": "http",
					"host": [
						"localhost"
					],
					"port": "8888",
					"path": [
						"mayakitchen",
						"API",
						"getSpecialOffers.php"
					],
					"query": [
						{
							"key": "",
							"value": null
						}
					]
				}
			},
			"response": []
		},
		{
			"name": "applyspecialoffers",
			"request": {
				"method": "POST",
				"header": [],
				"body": {
					"mode": "raw",
					"raw": "{\n    \"offer_id\": \"1\"\n}\n",
					"options": {
						"raw": {
							"language": "json"
						}
					}
				},
				"url": {
					"raw": "http://localhost:8888/mayakitchen/API/applySpecialOffers.php?id=7",
					"protocol": "http",
					"host": [
						"localhost"
					],
					"port": "8888",
					"path": [
						"mayakitchen",
						"API",
						"applySpecialOffers.php"
					],
					"query": [
						{
							"key": "id",
							"value": "7"
						}
					]
				}
			},
			"response": []
		},
		{
			"name": "GetDailySpecials",
			"protocolProfileBehavior": {
				"disableBodyPruning": true
			},
			"request": {
				"method": "GET",
				"header": [],
				"body": {
					"mode": "raw",
					"raw": "{\n    \"id\":\"2\"\n}",
					"options": {
						"raw": {
							"language": "json"
						}
					}
				},
				"url": {
					"raw": "http://localhost:8888/mayakitchen/API/GetDailySpecials.php?",
					"protocol": "http",
					"host": [
						"localhost"
					],
					"port": "8888",
					"path": [
						"mayakitchen",
						"API",
						"GetDailySpecials.php"
					],
					"query": [
						{
							"key": "",
							"value": null
						}
					]
				}
			},
			"response": []
		},
		{
			"name": "GetLoyaltyPoints",
			"protocolProfileBehavior": {
				"disableBodyPruning": true
			},
			"request": {
				"method": "GET",
				"header": [],
				"body": {
					"mode": "raw",
					"raw": "{\n    \"user_id\":\"1\"\n}",
					"options": {
						"raw": {
							"language": "json"
						}
					}
				},
				"url": {
					"raw": "http://localhost:8888/mayakitchen/API/GetLoyaltyPoints.php?",
					"protocol": "http",
					"host": [
						"localhost"
					],
					"port": "8888",
					"path": [
						"mayakitchen",
						"API",
						"GetLoyaltyPoints.php"
					],
					"query": [
						{
							"key": "",
							"value": null
						}
					]
				}
			},
			"response": []
		},
		{
			"name": "food menu",
			"request": {
				"method": "GET",
				"header": []
			},
			"response": []
		},
		{
			"name": "fooddetails",
			"protocolProfileBehavior": {
				"disableBodyPruning": true
			},
			"request": {
				"method": "GET",
				"header": [],
				"body": {
					"mode": "raw",
					"raw": "{\n    \"food_id\":\"9\"\n}",
					"options": {
						"raw": {
							"language": "json"
						}
					}
				},
				"url": {
					"raw": "http://localhost:8888/mayakitchen/API/GetFoodDetails.php?",
					"protocol": "http",
					"host": [
						"localhost"
					],
					"port": "8888",
					"path": [
						"mayakitchen",
						"API",
						"GetFoodDetails.php"
					],
					"query": [
						{
							"key": "",
							"value": null
						}
					]
				}
			},
			"response": []
		},
		{
			"name": "drink menu",
			"request": {
				"method": "GET",
				"header": [],
				"url": {
					"raw": "http://localhost:8888/mayakitchen/API/getdrinkmenu.php?",
					"protocol": "http",
					"host": [
						"localhost"
					],
					"port": "8888",
					"path": [
						"mayakitchen",
						"API",
						"getdrinkmenu.php"
					],
					"query": [
						{
							"key": "",
							"value": null
						}
					]
				}
			},
			"response": []
		},
		{
			"name": "drinkdetail",
			"protocolProfileBehavior": {
				"disableBodyPruning": true
			},
			"request": {
				"method": "GET",
				"header": [],
				"body": {
					"mode": "raw",
					"raw": "{\n    \"drink_id\":\"4\"\n}",
					"options": {
						"raw": {
							"language": "json"
						}
					}
				},
				"url": {
					"raw": "http://localhost:8888/mayakitchen/API/getDrinkDetail.php?",
					"protocol": "http",
					"host": [
						"localhost"
					],
					"port": "8888",
					"path": [
						"mayakitchen",
						"API",
						"getDrinkDetail.php"
					],
					"query": [
						{
							"key": "",
							"value": null
						}
					]
				}
			},
			"response": []
		},
		{
			"name": "viewEvents",
			"protocolProfileBehavior": {
				"disableBodyPruning": true
			},
			"request": {
				"method": "GET",
				"header": [],
				"body": {
					"mode": "raw",
					"raw": "{\n    \"user_id\":\"3\"\n}",
					"options": {
						"raw": {
							"language": "json"
						}
					}
				},
				"url": {
					"raw": "http://localhost:8888/mayakitchen/API/viewuserevents.php?",
					"protocol": "http",
					"host": [
						"localhost"
					],
					"port": "8888",
					"path": [
						"mayakitchen",
						"API",
						"viewuserevents.php"
					],
					"query": [
						{
							"key": "",
							"value": null
						}
					]
				}
			},
			"response": []
		}
	]
}